{
	"number": 81,
	"name": "سُورَةُ التَّكۡوِيرِ",
	"englishName": "At-Takwir",
	"englishNameTranslation": "The Overthrowing",
	"revelationType": "Meccan",
	"numberOfAyahs": 29,
	"ayahs": [
		{
			"number": 5801,
			"text": "«إذا الشمس كوِّرت» لففت وذهب بنورها.",
			"numberInSurah": 1,
			"juz": 30,
			"manzil": 7,
			"page": 586,
			"ruku": 523,
			"hizbQuarter": 234,
			"sajda": false
		},
		{
			"number": 5802,
			"text": "«وإذا النجوم انكدرت» انقضت وتساقطت على الأرض.",
			"numberInSurah": 2,
			"juz": 30,
			"manzil": 7,
			"page": 586,
			"ruku": 523,
			"hizbQuarter": 234,
			"sajda": false
		},
		{
			"number": 5803,
			"text": "«وإذا الجبال سيِّرت» ذهب بها عن وجه الأرض فصارت هباءً منبثا.",
			"numberInSurah": 3,
			"juz": 30,
			"manzil": 7,
			"page": 586,
			"ruku": 523,
			"hizbQuarter": 234,
			"sajda": false
		},
		{
			"number": 5804,
			"text": "«وإذا العشار» النوق الحوامل «عُطلت» تركت بلا راع أو بلا حلب لما دهاهم من الأمر، وإن لم يكن مال أعجب إليهم منها.",
			"numberInSurah": 4,
			"juz": 30,
			"manzil": 7,
			"page": 586,
			"ruku": 523,
			"hizbQuarter": 234,
			"sajda": false
		},
		{
			"number": 5805,
			"text": "«وإذا الوحوش حشرت» جمعت بعد البعث ليقتص لبعض من بعض ثم تصير ترابا.",
			"numberInSurah": 5,
			"juz": 30,
			"manzil": 7,
			"page": 586,
			"ruku": 523,
			"hizbQuarter": 234,
			"sajda": false
		},
		{
			"number": 5806,
			"text": "«وإذا البحار سجِّرت» بالتخفيف والتشديد: أوقدت فصارت نارا.",
			"numberInSurah": 6,
			"juz": 30,
			"manzil": 7,
			"page": 586,
			"ruku": 523,
			"hizbQuarter": 234,
			"sajda": false
		},
		{
			"number": 5807,
			"text": "«وإذا النفوس زوجت» قرنت بأجسادها.",
			"numberInSurah": 7,
			"juz": 30,
			"manzil": 7,
			"page": 586,
			"ruku": 523,
			"hizbQuarter": 234,
			"sajda": false
		},
		{
			"number": 5808,
			"text": "«وإذا الموءودة» الجارية تدفن حية خوف العار والحاجة «سئلت» تبكيتا لقاتلها.",
			"numberInSurah": 8,
			"juz": 30,
			"manzil": 7,
			"page": 586,
			"ruku": 523,
			"hizbQuarter": 234,
			"sajda": false
		},
		{
			"number": 5809,
			"text": "«بأي ذنب قتلت» وقرئ بكسر التاء حكاية لما تخاطب به وجوابها أن تقول: قتلت بلا ذنب.",
			"numberInSurah": 9,
			"juz": 30,
			"manzil": 7,
			"page": 586,
			"ruku": 523,
			"hizbQuarter": 234,
			"sajda": false
		},
		{
			"number": 5810,
			"text": "«وإذا الصحف» صحف الأعمال «نشرت» بالتخفيف والتشديد فتح وبسطت.",
			"numberInSurah": 10,
			"juz": 30,
			"manzil": 7,
			"page": 586,
			"ruku": 523,
			"hizbQuarter": 234,
			"sajda": false
		},
		{
			"number": 5811,
			"text": "«وإذا السماء كشطت» نزعت عن أماكنها كما ينزع الجلد عن الشاة.",
			"numberInSurah": 11,
			"juz": 30,
			"manzil": 7,
			"page": 586,
			"ruku": 523,
			"hizbQuarter": 234,
			"sajda": false
		},
		{
			"number": 5812,
			"text": "«وإذا الجحيم» النار «سعرت» بالتخفيف والتشديد أُججت.",
			"numberInSurah": 12,
			"juz": 30,
			"manzil": 7,
			"page": 586,
			"ruku": 523,
			"hizbQuarter": 234,
			"sajda": false
		},
		{
			"number": 5813,
			"text": "«وإذا الجنة أزلفت» قربت لأهلها ليدخلوها وجواب إذا أول السورة وما عطف عليها.",
			"numberInSurah": 13,
			"juz": 30,
			"manzil": 7,
			"page": 586,
			"ruku": 523,
			"hizbQuarter": 234,
			"sajda": false
		},
		{
			"number": 5814,
			"text": "«علمت نفس» كل نفس وقت هذه المذكورات وهو يوم القيامة «ما أحضرت» من خير وشر.",
			"numberInSurah": 14,
			"juz": 30,
			"manzil": 7,
			"page": 586,
			"ruku": 523,
			"hizbQuarter": 234,
			"sajda": false
		},
		{
			"number": 5815,
			"text": "«فلا أقسم» لا زائدة «بالخُنَّس».",
			"numberInSurah": 15,
			"juz": 30,
			"manzil": 7,
			"page": 586,
			"ruku": 523,
			"hizbQuarter": 234,
			"sajda": false
		},
		{
			"number": 5816,
			"text": "«الجوار الكنَّس» هي النجوم الخمسة: زحل والمشتري والمريخ والزهرة وعطارد، تخنس بضم النون، أي ترجع في مجراها وراءها، بينما نرى النجم في آخر البرج إذ كَّر راجعا إلى أوله، وتكنس بكسر النون: تدخل في كناسها، أي تغيب في المواضع التي تغيب فيها.",
			"numberInSurah": 16,
			"juz": 30,
			"manzil": 7,
			"page": 586,
			"ruku": 523,
			"hizbQuarter": 234,
			"sajda": false
		},
		{
			"number": 5817,
			"text": "«والليل إذا عسعس» أقبل بظلامه أو أدبر.",
			"numberInSurah": 17,
			"juz": 30,
			"manzil": 7,
			"page": 586,
			"ruku": 523,
			"hizbQuarter": 234,
			"sajda": false
		},
		{
			"number": 5818,
			"text": "«والصبح إذا تنفس» امتد حتى يصير نهارا بينا.",
			"numberInSurah": 18,
			"juz": 30,
			"manzil": 7,
			"page": 586,
			"ruku": 523,
			"hizbQuarter": 234,
			"sajda": false
		},
		{
			"number": 5819,
			"text": "«إنه» أي القرآن «لقول رسول كريم» على الله تعالى وهو جبريل أضيف إليه لنزوله به.",
			"numberInSurah": 19,
			"juz": 30,
			"manzil": 7,
			"page": 586,
			"ruku": 523,
			"hizbQuarter": 234,
			"sajda": false
		},
		{
			"number": 5820,
			"text": "«ذي قوة» أي شديد القوى «عند ذي العرش» أي الله تعالى «مكين» ذي مكانة متعلق به عند.",
			"numberInSurah": 20,
			"juz": 30,
			"manzil": 7,
			"page": 586,
			"ruku": 523,
			"hizbQuarter": 234,
			"sajda": false
		},
		{
			"number": 5821,
			"text": "«مطاع ثَمَّ» تطيعه الملائكة في السماوات «أمين» على الوحي.",
			"numberInSurah": 21,
			"juz": 30,
			"manzil": 7,
			"page": 586,
			"ruku": 523,
			"hizbQuarter": 234,
			"sajda": false
		},
		{
			"number": 5822,
			"text": "«وما صاحبكم» محمد صلى الله عليه وسلم عطف على إنه إلى آخر المقسم عليه «بمجنون» كما زعمتم.",
			"numberInSurah": 22,
			"juz": 30,
			"manzil": 7,
			"page": 586,
			"ruku": 523,
			"hizbQuarter": 234,
			"sajda": false
		},
		{
			"number": 5823,
			"text": "«ولقد رآه» رأى محمد صلى الله عليه وسلم جبريل على صورته التي خُلق عليها «بالأفق المبين» البيِّن وهو الأعلى بناحية المشرق.",
			"numberInSurah": 23,
			"juz": 30,
			"manzil": 7,
			"page": 586,
			"ruku": 523,
			"hizbQuarter": 234,
			"sajda": false
		},
		{
			"number": 5824,
			"text": "«وما هو» محمد صلى الله عليه وسلم «على الغيب» ما غاب من الوحي وخبر السماء «بظنين» أي بمتهم، وفي قراءة بالضاد، أي ببخيل فينتقص شيئا منه.",
			"numberInSurah": 24,
			"juz": 30,
			"manzil": 7,
			"page": 586,
			"ruku": 523,
			"hizbQuarter": 234,
			"sajda": false
		},
		{
			"number": 5825,
			"text": "«وما هو» أي القرآن «بقول شيطان» مسترق السمع «رجيم» مرجوم.",
			"numberInSurah": 25,
			"juz": 30,
			"manzil": 7,
			"page": 586,
			"ruku": 523,
			"hizbQuarter": 234,
			"sajda": false
		},
		{
			"number": 5826,
			"text": "«فأين تذهبون» فبأي طريق تسلكون في إنكاركم القرآن وإعراضكم عنه.",
			"numberInSurah": 26,
			"juz": 30,
			"manzil": 7,
			"page": 586,
			"ruku": 523,
			"hizbQuarter": 234,
			"sajda": false
		},
		{
			"number": 5827,
			"text": "«إن» ما «هو إلا ذكر» عظة «للعالمين» الإنس والجن.",
			"numberInSurah": 27,
			"juz": 30,
			"manzil": 7,
			"page": 586,
			"ruku": 523,
			"hizbQuarter": 234,
			"sajda": false
		},
		{
			"number": 5828,
			"text": "«لمن شاء منكم» بدل من العالمين بإعادة الجار «أن يستقيم» باتباع الحق.",
			"numberInSurah": 28,
			"juz": 30,
			"manzil": 7,
			"page": 586,
			"ruku": 523,
			"hizbQuarter": 234,
			"sajda": false
		},
		{
			"number": 5829,
			"text": "«وما تشاءون» الاستقامة على حق «إلا أن يشاء الله رب العالمين» الخلائق استقامتكم عليه.",
			"numberInSurah": 29,
			"juz": 30,
			"manzil": 7,
			"page": 586,
			"ruku": 523,
			"hizbQuarter": 234,
			"sajda": false
		}
	],
	"edition": {
		"identifier": "ar.jalalayn",
		"language": "ar",
		"name": "تفسير الجلالين",
		"englishName": "Jalal ad-Din al-Mahalli and Jalal ad-Din as-Suyuti",
		"format": "text",
		"type": "tafsir",
		"direction": "rtl"
	}
}