{
	"number": 447,
	"ayahs": [
		{
			"number": 3813,
			"text": "مَا لَكُمْ لَا تَنَاصَرُونَ",
			"surah": {
				"number": 37,
				"name": "سُورَةُ الصَّافَّاتِ",
				"englishName": "As-Saaffaat",
				"englishNameTranslation": "Those drawn up in Ranks",
				"revelationType": "Meccan",
				"numberOfAyahs": 182
			},
			"numberInSurah": 25,
			"juz": 23,
			"manzil": 6,
			"page": 447,
			"ruku": 387,
			"hizbQuarter": 179,
			"sajda": false
		},
		{
			"number": 3814,
			"text": "بَلْ هُمُ الْيَوْمَ مُسْتَسْلِمُونَ",
			"surah": {
				"number": 37,
				"name": "سُورَةُ الصَّافَّاتِ",
				"englishName": "As-Saaffaat",
				"englishNameTranslation": "Those drawn up in Ranks",
				"revelationType": "Meccan",
				"numberOfAyahs": 182
			},
			"numberInSurah": 26,
			"juz": 23,
			"manzil": 6,
			"page": 447,
			"ruku": 387,
			"hizbQuarter": 179,
			"sajda": false
		},
		{
			"number": 3815,
			"text": "وَأَقْبَلَ بَعْضُهُمْ عَلَىٰ بَعْضٍ يَتَسَاءَلُونَ",
			"surah": {
				"number": 37,
				"name": "سُورَةُ الصَّافَّاتِ",
				"englishName": "As-Saaffaat",
				"englishNameTranslation": "Those drawn up in Ranks",
				"revelationType": "Meccan",
				"numberOfAyahs": 182
			},
			"numberInSurah": 27,
			"juz": 23,
			"manzil": 6,
			"page": 447,
			"ruku": 387,
			"hizbQuarter": 179,
			"sajda": false
		},
		{
			"number": 3816,
			"text": "قَالُوا إِنَّكُمْ كُنْتُمْ تَأْتُونَنَا عَنِ الْيَمِينِ",
			"surah": {
				"number": 37,
				"name": "سُورَةُ الصَّافَّاتِ",
				"englishName": "As-Saaffaat",
				"englishNameTranslation": "Those drawn up in Ranks",
				"revelationType": "Meccan",
				"numberOfAyahs": 182
			},
			"numberInSurah": 28,
			"juz": 23,
			"manzil": 6,
			"page": 447,
			"ruku": 387,
			"hizbQuarter": 179,
			"sajda": false
		},
		{
			"number": 3817,
			"text": "قَالُوا بَلْ لَمْ تَكُونُوا مُؤْمِنِينَ",
			"surah": {
				"number": 37,
				"name": "سُورَةُ الصَّافَّاتِ",
				"englishName": "As-Saaffaat",
				"englishNameTranslation": "Those drawn up in Ranks",
				"revelationType": "Meccan",
				"numberOfAyahs": 182
			},
			"numberInSurah": 29,
			"juz": 23,
			"manzil": 6,
			"page": 447,
			"ruku": 387,
			"hizbQuarter": 179,
			"sajda": false
		},
		{
			"number": 3818,
			"text": "وَمَا كَانَ لَنَا عَلَيْكُمْ مِنْ سُلْطَانٍ ۖ بَلْ كُنْتُمْ قَوْمًا طَاغِينَ",
			"surah": {
				"number": 37,
				"name": "سُورَةُ الصَّافَّاتِ",
				"englishName": "As-Saaffaat",
				"englishNameTranslation": "Those drawn up in Ranks",
				"revelationType": "Meccan",
				"numberOfAyahs": 182
			},
			"numberInSurah": 30,
			"juz": 23,
			"manzil": 6,
			"page": 447,
			"ruku": 387,
			"hizbQuarter": 179,
			"sajda": false
		},
		{
			"number": 3819,
			"text": "فَحَقَّ عَلَيْنَا قَوْلُ رَبِّنَا ۖ إِنَّا لَذَائِقُونَ",
			"surah": {
				"number": 37,
				"name": "سُورَةُ الصَّافَّاتِ",
				"englishName": "As-Saaffaat",
				"englishNameTranslation": "Those drawn up in Ranks",
				"revelationType": "Meccan",
				"numberOfAyahs": 182
			},
			"numberInSurah": 31,
			"juz": 23,
			"manzil": 6,
			"page": 447,
			"ruku": 387,
			"hizbQuarter": 179,
			"sajda": false
		},
		{
			"number": 3820,
			"text": "فَأَغْوَيْنَاكُمْ إِنَّا كُنَّا غَاوِينَ",
			"surah": {
				"number": 37,
				"name": "سُورَةُ الصَّافَّاتِ",
				"englishName": "As-Saaffaat",
				"englishNameTranslation": "Those drawn up in Ranks",
				"revelationType": "Meccan",
				"numberOfAyahs": 182
			},
			"numberInSurah": 32,
			"juz": 23,
			"manzil": 6,
			"page": 447,
			"ruku": 387,
			"hizbQuarter": 179,
			"sajda": false
		},
		{
			"number": 3821,
			"text": "فَإِنَّهُمْ يَوْمَئِذٍ فِي الْعَذَابِ مُشْتَرِكُونَ",
			"surah": {
				"number": 37,
				"name": "سُورَةُ الصَّافَّاتِ",
				"englishName": "As-Saaffaat",
				"englishNameTranslation": "Those drawn up in Ranks",
				"revelationType": "Meccan",
				"numberOfAyahs": 182
			},
			"numberInSurah": 33,
			"juz": 23,
			"manzil": 6,
			"page": 447,
			"ruku": 387,
			"hizbQuarter": 179,
			"sajda": false
		},
		{
			"number": 3822,
			"text": "إِنَّا كَذَٰلِكَ نَفْعَلُ بِالْمُجْرِمِينَ",
			"surah": {
				"number": 37,
				"name": "سُورَةُ الصَّافَّاتِ",
				"englishName": "As-Saaffaat",
				"englishNameTranslation": "Those drawn up in Ranks",
				"revelationType": "Meccan",
				"numberOfAyahs": 182
			},
			"numberInSurah": 34,
			"juz": 23,
			"manzil": 6,
			"page": 447,
			"ruku": 387,
			"hizbQuarter": 179,
			"sajda": false
		},
		{
			"number": 3823,
			"text": "إِنَّهُمْ كَانُوا إِذَا قِيلَ لَهُمْ لَا إِلَٰهَ إِلَّا اللَّهُ يَسْتَكْبِرُونَ",
			"surah": {
				"number": 37,
				"name": "سُورَةُ الصَّافَّاتِ",
				"englishName": "As-Saaffaat",
				"englishNameTranslation": "Those drawn up in Ranks",
				"revelationType": "Meccan",
				"numberOfAyahs": 182
			},
			"numberInSurah": 35,
			"juz": 23,
			"manzil": 6,
			"page": 447,
			"ruku": 387,
			"hizbQuarter": 179,
			"sajda": false
		},
		{
			"number": 3824,
			"text": "وَيَقُولُونَ أَئِنَّا لَتَارِكُو آلِهَتِنَا لِشَاعِرٍ مَجْنُونٍ",
			"surah": {
				"number": 37,
				"name": "سُورَةُ الصَّافَّاتِ",
				"englishName": "As-Saaffaat",
				"englishNameTranslation": "Those drawn up in Ranks",
				"revelationType": "Meccan",
				"numberOfAyahs": 182
			},
			"numberInSurah": 36,
			"juz": 23,
			"manzil": 6,
			"page": 447,
			"ruku": 387,
			"hizbQuarter": 179,
			"sajda": false
		},
		{
			"number": 3825,
			"text": "بَلْ جَاءَ بِالْحَقِّ وَصَدَّقَ الْمُرْسَلِينَ",
			"surah": {
				"number": 37,
				"name": "سُورَةُ الصَّافَّاتِ",
				"englishName": "As-Saaffaat",
				"englishNameTranslation": "Those drawn up in Ranks",
				"revelationType": "Meccan",
				"numberOfAyahs": 182
			},
			"numberInSurah": 37,
			"juz": 23,
			"manzil": 6,
			"page": 447,
			"ruku": 387,
			"hizbQuarter": 179,
			"sajda": false
		},
		{
			"number": 3826,
			"text": "إِنَّكُمْ لَذَائِقُو الْعَذَابِ الْأَلِيمِ",
			"surah": {
				"number": 37,
				"name": "سُورَةُ الصَّافَّاتِ",
				"englishName": "As-Saaffaat",
				"englishNameTranslation": "Those drawn up in Ranks",
				"revelationType": "Meccan",
				"numberOfAyahs": 182
			},
			"numberInSurah": 38,
			"juz": 23,
			"manzil": 6,
			"page": 447,
			"ruku": 387,
			"hizbQuarter": 179,
			"sajda": false
		},
		{
			"number": 3827,
			"text": "وَمَا تُجْزَوْنَ إِلَّا مَا كُنْتُمْ تَعْمَلُونَ",
			"surah": {
				"number": 37,
				"name": "سُورَةُ الصَّافَّاتِ",
				"englishName": "As-Saaffaat",
				"englishNameTranslation": "Those drawn up in Ranks",
				"revelationType": "Meccan",
				"numberOfAyahs": 182
			},
			"numberInSurah": 39,
			"juz": 23,
			"manzil": 6,
			"page": 447,
			"ruku": 387,
			"hizbQuarter": 179,
			"sajda": false
		},
		{
			"number": 3828,
			"text": "إِلَّا عِبَادَ اللَّهِ الْمُخْلَصِينَ",
			"surah": {
				"number": 37,
				"name": "سُورَةُ الصَّافَّاتِ",
				"englishName": "As-Saaffaat",
				"englishNameTranslation": "Those drawn up in Ranks",
				"revelationType": "Meccan",
				"numberOfAyahs": 182
			},
			"numberInSurah": 40,
			"juz": 23,
			"manzil": 6,
			"page": 447,
			"ruku": 387,
			"hizbQuarter": 179,
			"sajda": false
		},
		{
			"number": 3829,
			"text": "أُولَٰئِكَ لَهُمْ رِزْقٌ مَعْلُومٌ",
			"surah": {
				"number": 37,
				"name": "سُورَةُ الصَّافَّاتِ",
				"englishName": "As-Saaffaat",
				"englishNameTranslation": "Those drawn up in Ranks",
				"revelationType": "Meccan",
				"numberOfAyahs": 182
			},
			"numberInSurah": 41,
			"juz": 23,
			"manzil": 6,
			"page": 447,
			"ruku": 387,
			"hizbQuarter": 179,
			"sajda": false
		},
		{
			"number": 3830,
			"text": "فَوَاكِهُ ۖ وَهُمْ مُكْرَمُونَ",
			"surah": {
				"number": 37,
				"name": "سُورَةُ الصَّافَّاتِ",
				"englishName": "As-Saaffaat",
				"englishNameTranslation": "Those drawn up in Ranks",
				"revelationType": "Meccan",
				"numberOfAyahs": 182
			},
			"numberInSurah": 42,
			"juz": 23,
			"manzil": 6,
			"page": 447,
			"ruku": 387,
			"hizbQuarter": 179,
			"sajda": false
		},
		{
			"number": 3831,
			"text": "فِي جَنَّاتِ النَّعِيمِ",
			"surah": {
				"number": 37,
				"name": "سُورَةُ الصَّافَّاتِ",
				"englishName": "As-Saaffaat",
				"englishNameTranslation": "Those drawn up in Ranks",
				"revelationType": "Meccan",
				"numberOfAyahs": 182
			},
			"numberInSurah": 43,
			"juz": 23,
			"manzil": 6,
			"page": 447,
			"ruku": 387,
			"hizbQuarter": 179,
			"sajda": false
		},
		{
			"number": 3832,
			"text": "عَلَىٰ سُرُرٍ مُتَقَابِلِينَ",
			"surah": {
				"number": 37,
				"name": "سُورَةُ الصَّافَّاتِ",
				"englishName": "As-Saaffaat",
				"englishNameTranslation": "Those drawn up in Ranks",
				"revelationType": "Meccan",
				"numberOfAyahs": 182
			},
			"numberInSurah": 44,
			"juz": 23,
			"manzil": 6,
			"page": 447,
			"ruku": 387,
			"hizbQuarter": 179,
			"sajda": false
		},
		{
			"number": 3833,
			"text": "يُطَافُ عَلَيْهِمْ بِكَأْسٍ مِنْ مَعِينٍ",
			"surah": {
				"number": 37,
				"name": "سُورَةُ الصَّافَّاتِ",
				"englishName": "As-Saaffaat",
				"englishNameTranslation": "Those drawn up in Ranks",
				"revelationType": "Meccan",
				"numberOfAyahs": 182
			},
			"numberInSurah": 45,
			"juz": 23,
			"manzil": 6,
			"page": 447,
			"ruku": 387,
			"hizbQuarter": 179,
			"sajda": false
		},
		{
			"number": 3834,
			"text": "بَيْضَاءَ لَذَّةٍ لِلشَّارِبِينَ",
			"surah": {
				"number": 37,
				"name": "سُورَةُ الصَّافَّاتِ",
				"englishName": "As-Saaffaat",
				"englishNameTranslation": "Those drawn up in Ranks",
				"revelationType": "Meccan",
				"numberOfAyahs": 182
			},
			"numberInSurah": 46,
			"juz": 23,
			"manzil": 6,
			"page": 447,
			"ruku": 387,
			"hizbQuarter": 179,
			"sajda": false
		},
		{
			"number": 3835,
			"text": "لَا فِيهَا غَوْلٌ وَلَا هُمْ عَنْهَا يُنْزَفُونَ",
			"surah": {
				"number": 37,
				"name": "سُورَةُ الصَّافَّاتِ",
				"englishName": "As-Saaffaat",
				"englishNameTranslation": "Those drawn up in Ranks",
				"revelationType": "Meccan",
				"numberOfAyahs": 182
			},
			"numberInSurah": 47,
			"juz": 23,
			"manzil": 6,
			"page": 447,
			"ruku": 387,
			"hizbQuarter": 179,
			"sajda": false
		},
		{
			"number": 3836,
			"text": "وَعِنْدَهُمْ قَاصِرَاتُ الطَّرْفِ عِينٌ",
			"surah": {
				"number": 37,
				"name": "سُورَةُ الصَّافَّاتِ",
				"englishName": "As-Saaffaat",
				"englishNameTranslation": "Those drawn up in Ranks",
				"revelationType": "Meccan",
				"numberOfAyahs": 182
			},
			"numberInSurah": 48,
			"juz": 23,
			"manzil": 6,
			"page": 447,
			"ruku": 387,
			"hizbQuarter": 179,
			"sajda": false
		},
		{
			"number": 3837,
			"text": "كَأَنَّهُنَّ بَيْضٌ مَكْنُونٌ",
			"surah": {
				"number": 37,
				"name": "سُورَةُ الصَّافَّاتِ",
				"englishName": "As-Saaffaat",
				"englishNameTranslation": "Those drawn up in Ranks",
				"revelationType": "Meccan",
				"numberOfAyahs": 182
			},
			"numberInSurah": 49,
			"juz": 23,
			"manzil": 6,
			"page": 447,
			"ruku": 387,
			"hizbQuarter": 179,
			"sajda": false
		},
		{
			"number": 3838,
			"text": "فَأَقْبَلَ بَعْضُهُمْ عَلَىٰ بَعْضٍ يَتَسَاءَلُونَ",
			"surah": {
				"number": 37,
				"name": "سُورَةُ الصَّافَّاتِ",
				"englishName": "As-Saaffaat",
				"englishNameTranslation": "Those drawn up in Ranks",
				"revelationType": "Meccan",
				"numberOfAyahs": 182
			},
			"numberInSurah": 50,
			"juz": 23,
			"manzil": 6,
			"page": 447,
			"ruku": 387,
			"hizbQuarter": 179,
			"sajda": false
		},
		{
			"number": 3839,
			"text": "قَالَ قَائِلٌ مِنْهُمْ إِنِّي كَانَ لِي قَرِينٌ",
			"surah": {
				"number": 37,
				"name": "سُورَةُ الصَّافَّاتِ",
				"englishName": "As-Saaffaat",
				"englishNameTranslation": "Those drawn up in Ranks",
				"revelationType": "Meccan",
				"numberOfAyahs": 182
			},
			"numberInSurah": 51,
			"juz": 23,
			"manzil": 6,
			"page": 447,
			"ruku": 387,
			"hizbQuarter": 179,
			"sajda": false
		}
	],
	"surahs": {
		"37": {
			"number": 37,
			"name": "سُورَةُ الصَّافَّاتِ",
			"englishName": "As-Saaffaat",
			"englishNameTranslation": "Those drawn up in Ranks",
			"revelationType": "Meccan",
			"numberOfAyahs": 182
		}
	},
	"edition": {
		"identifier": "quran-simple",
		"language": "ar",
		"name": "القرآن الكريم المبسط (تشكيل بسيط)",
		"englishName": "Simple",
		"format": "text",
		"type": "quran",
		"direction": "rtl"
	}
}